Workbook
Name ReportDate: DATE(2026,4,7)

Sheet GRC Risk Register
A1: GRC RISK REGISTER — KTECH
A2: Organisation: KTECH | Sector: SaaS / Cloud Technology | Regulated by: ICO, FCA (payments) | Attestations: SOC 2 Type II, ISO 27001 | Framework: ISO 31000 / NIST CSF | Version: 1.0 | Last Updated: 07 April 2026 | Classification: Portfolio Demonstration
A4: RISK IDENTIFICATION | D4: DOMAIN & OWNERSHIP | F4: INHERENT RISK ← AUTO | J4: CONTROL ENVIRONMENT | M4: RESIDUAL RISK ← AUTO | Q4: TREATMENT & TRACKING | T4: AUDIT / REVIEW
A5: Risk ID | B5: Risk Title | C5: Risk Description | D5: Risk Domain | E5: Risk Owner (Role) | F5: Likelihood (1–5) | G5: Impact (1–5) | H5: Inherent Score ⚡ | I5: Inherent Rating ⚡ | J5: Control Description | K5: Control Effectiveness | L5: Control Owner (Role) | M5: Residual Likelihood | N5: Residual Impact | O5: Residual Score ⚡ | P5: Residual Rating ⚡ | Q5: Treatment Action | R5: Accountable Role | S5: Target Date | T5: Last Review Date | U5: Review Status
A6: TC-001 | B6: Inadequate Enterprise Risk Governance | C6: No formal ERM framework means risks are managed in silos, creating blind spots and delayed executive response. | D6: Governance | E6: Chief Risk Officer (CRO) | F6: 3 | G6: 4 | H6: =F6*G6 -> 12 | I6: =IF(H6>=20,"Critical",IF(H6>=12,"High",IF(H6>=6,"Medium",IF(H6>=2,"Low","Informational")))) -> High | J6: Risk committee established; quarterly risk reporting; risk appetite statement drafted. | K6: Basic | L6: Chief Risk Officer (CRO) | M6: 3 | N6: 3 | O6: =M6*N6 -> 9 | P6: =IF(O6>=20,"Critical",IF(O6>=12,"High",IF(O6>=6,"Medium",IF(O6>=2,"Low","Informational")))) -> Medium | Q6: Formalise ERM framework; appoint risk champions per business unit; launch risk culture survey. | R6: Chief Risk Officer (CRO) | S6: 46203 | T6: 45962 | U6: In Progress
A7: TC-002 | B7: Cloud Infrastructure Failure | C7: Outage of primary cloud provider (AWS/Azure/GCP) causes platform downtime, SLA breach and revenue loss. | D7: Information Technology | E7: IT Director | F7: 3 | G7: 5 | H7: =F7*G7 -> 15 | I7: =IF(H7>=20,"Critical",IF(H7>=12,"High",IF(H7>=6,"Medium",IF(H7>=2,"Low","Informational")))) -> High | J7: Multi-AZ deployment; automated failover; 99.9% SLA with cloud provider; monthly DR tests. | K7: Strong | L7: IT Director | M7: 1 | N7: 5 | O7: =M7*N7 -> 5 | P7: =IF(O7>=20,"Critical",IF(O7>=12,"High",IF(O7>=6,"Medium",IF(O7>=2,"Low","Informational")))) -> Low | Q7: Implement multi-region active-active architecture; quarterly failover drills; chaos engineering. | R7: IT Director | S7: 46203 | T7: 45992 | U7: In Progress
A8: TC-003 | B8: Software Supply Chain Attack | C8: Malicious code injected into open-source dependencies or CI/CD pipeline compromises production systems. | D8: Information Technology | E8: Chief Information Security Officer (CISO) | F8: 3 | G8: 5 | H8: =F8*G8 -> 15 | I8: =IF(H8>=20,"Critical",IF(H8>=12,"High",IF(H8>=6,"Medium",IF(H8>=2,"Low","Informational")))) -> High | J8: SBOM generated for major releases; Dependabot alerts active; SCA tooling in CI pipeline. | K8: Adequate | L8: Chief Information Security Officer (CISO) | M8: 2 | N8: 5 | O8: =M8*N8 -> 10 | P8: =IF(O8>=20,"Critical",IF(O8>=12,"High",IF(O8>=6,"Medium",IF(O8>=2,"Low","Informational")))) -> Medium | Q8: Mandate SBOM for all releases; deploy Sigstore signing; conduct supply chain risk assessment. | R8: Chief Information Security Officer (CISO) | S8: 46142 | T8: 45976 | U8: Open
A9: TC-004 | B9: Zero-Day Vulnerability Exploitation | C9: Unknown vulnerability in product or infrastructure exploited before patch available, causing data breach. | D9: Information Technology | E9: Chief Information Security Officer (CISO) | F9: 3 | G9: 5 | H9: =F9*G9 -> 15 | I9: =IF(H9>=20,"Critical",IF(H9>=12,"High",IF(H9>=6,"Medium",IF(H9>=2,"Low","Informational")))) -> High | J9: Bug bounty programme active; WAF deployed; 24/7 SIEM monitoring; threat intelligence feeds. | K9: Adequate | L9: Chief Information Security Officer (CISO) | M9: 2 | N9: 4 | O9: =M9*N9 -> 8 | P9: =IF(O9>=20,"Critical",IF(O9>=12,"High",IF(O9>=6,"Medium",IF(O9>=2,"Low","Informational")))) -> Medium | Q9: Reduce mean time to detect to <4hrs; integrate threat intel into SOAR; expand bug bounty scope. | R9: Chief Information Security Officer (CISO) | S9: 46173 | T9: 45950 | U9: Open
A10: TC-005 | B10: Customer Data Breach (GDPR/CCPA) | C10: Unauthorised access to customer PII triggers regulatory fines, customer churn and reputational damage. | D10: Information Technology | E10: Data Protection Officer (DPO) | F10: 3 | G10: 5 | H10: =F10*G10 -> 15 | I10: =IF(H10>=20,"Critical",IF(H10>=12,"High",IF(H10>=6,"Medium",IF(H10>=2,"Low","Informational")))) -> High | J10: Encryption at rest & in transit; RBAC enforced; DLP tooling deployed; DPO appointed. | K10: Adequate | L10: Data Protection Officer (DPO) | M10: 2 | N10: 4 | O10: =M10*N10 -> 8 | P10: =IF(O10>=20,"Critical",IF(O10>=12,"High",IF(O10>=6,"Medium",IF(O10>=2,"Low","Informational")))) -> Medium | Q10: Implement data discovery & classification; complete Article 30 records; conduct DPIA for AI features. | R10: Data Protection Officer (DPO) | S10: 46157 | T10: 45992 | U10: In Progress
A11: TC-006 | B11: Privileged Access & Insider Threat | C11: Excessive or unchecked privileged access exploited by insiders or compromised admin accounts. | D11: Information Technology | E11: Chief Information Security Officer (CISO) | F11: 3 | G11: 4 | H11: =F11*G11 -> 12 | I11: =IF(H11>=20,"Critical",IF(H11>=12,"High",IF(H11>=6,"Medium",IF(H11>=2,"Low","Informational")))) -> High | J11: PAM solution deployed for 70% of critical systems; MFA enforced for all admin accounts. | K11: Adequate | L11: IT Director | M11: 2 | N11: 3 | O11: =M11*N11 -> 6 | P11: =IF(O11>=20,"Critical",IF(O11>=12,"High",IF(O11>=6,"Medium",IF(O11>=2,"Low","Informational")))) -> Medium | Q11: Full PAM rollout; enforce JIT access; complete quarterly privileged access reviews. | R11: IT Director | S11: 46234 | T11: 45901 | U11: In Progress
A12: TC-007 | B12: Developer Talent Attrition | C12: Loss of senior engineers and scarce AI/ML talent to competitors disrupts product roadmap and innovation capacity. | D12: Human Resources | E12: Chief People Officer (CPO) | F12: 4 | G12: 4 | H12: =F12*G12 -> 16 | I12: =IF(H12>=20,"Critical",IF(H12>=12,"High",IF(H12>=6,"Medium",IF(H12>=2,"Low","Informational")))) -> High | J12: Retention bonuses for key engineers; career ladder framework; quarterly engagement surveys. | K12: Basic | L12: Chief People Officer (CPO) | M12: 3 | N12: 4 | O12: =M12*N12 -> 12 | P12: =IF(O12>=20,"Critical",IF(O12>=12,"High",IF(O12>=6,"Medium",IF(O12>=2,"Low","Informational")))) -> High | Q12: Introduce technical career progression tracks; publish engineering brand externally; benchmark comp annually. | R12: Chief People Officer (CPO) | S12: 46203 | T12: 45931 | U12: Open
A13: TC-008 | B13: AI / ML Skills Gap | C13: Inability to hire or upskill staff in generative AI, MLOps and data science limits product competitiveness. | D13: Human Resources | E13: Chief People Officer (CPO) | F13: 3 | G13: 4 | H13: =F13*G13 -> 12 | I13: =IF(H13>=20,"Critical",IF(H13>=12,"High",IF(H13>=6,"Medium",IF(H13>=2,"Low","Informational")))) -> High | J13: Learning budget of £3K/head; partnerships with 2 universities; internal AI guild active. | K13: Basic | L13: Chief People Officer (CPO) | M13: 3 | N13: 3 | O13: =M13*N13 -> 9 | P13: =IF(O13>=20,"Critical",IF(O13>=12,"High",IF(O13>=6,"Medium",IF(O13>=2,"Low","Informational")))) -> Medium | Q13: Launch AI upskilling programme; partner with bootcamps; establish internal AI Centre of Excellence. | R13: Chief People Officer (CPO) | S13: 46295 | T13: 45962 | U13: Open
A14: TC-009 | B14: Remote Work Security & Culture Risk | C14: Distributed workforce increases insider threat surface, erodes culture and creates inconsistent security practices. | D14: Human Resources | E14: Chief People Officer (CPO) | F14: 3 | G14: 3 | H14: =F14*G14 -> 9 | I14: =IF(H14>=20,"Critical",IF(H14>=12,"High",IF(H14>=6,"Medium",IF(H14>=2,"Low","Informational")))) -> Medium | J14: Security awareness training bi-annually; VPN mandated; endpoint management (MDM) in place. | K14: Adequate | L14: Chief Information Security Officer (CISO) | M14: 2 | N14: 3 | O14: =M14*N14 -> 6 | P14: =IF(O14>=20,"Critical",IF(O14>=12,"High",IF(O14>=6,"Medium",IF(O14>=2,"Low","Informational")))) -> Medium | Q14: Annual phishing simulation; mandatory device compliance check; introduce culture measurement framework. | R14: Chief Information Security Officer (CISO) | S14: 46142 | T14: 45945 | U14: In Progress
A15: TC-010 | B15: Diversity, Equity & Inclusion (DEI) Compliance | C15: Failure to meet gender pay gap reporting obligations or DEI targets triggers reputational damage and talent risks. | D15: Human Resources | E15: Chief People Officer (CPO) | F15: 2 | G15: 3 | H15: =F15*G15 -> 6 | I15: =IF(H15>=20,"Critical",IF(H15>=12,"High",IF(H15>=6,"Medium",IF(H15>=2,"Low","Informational")))) -> Medium | J15: Annual gender pay gap report published; D&I committee active; unconscious bias training mandatory. | K15: Adequate | L15: Chief People Officer (CPO) | M15: 1 | N15: 3 | O15: =M15*N15 -> 3 | P15: =IF(O15>=20,"Critical",IF(O15>=12,"High",IF(O15>=6,"Medium",IF(O15>=2,"Low","Informational")))) -> Low | Q15: Set measurable DEI targets; publish progress quarterly; integrate DEI into exec scorecards. | R15: Chief People Officer (CPO) | S15: 46387 | T15: 45962 | U15: In Progress
A16: TC-011 | B16: Critical Product Defect / Outage | C16: Severe bug in production release causes customer data loss, SLA breach or platform-wide outage. | D16: Product & Engineering | E16: Chief Technology Officer (CTO) | F16: 3 | G16: 4 | H16: =F16*G16 -> 12 | I16: =IF(H16>=20,"Critical",IF(H16>=12,"High",IF(H16>=6,"Medium",IF(H16>=2,"Low","Informational")))) -> High | J16: Automated test coverage >80%; staged rollout (canary); on-call SRE rotation; incident runbooks. | K16: Adequate | L16: Chief Technology Officer (CTO) | M16: 2 | N16: 3 | O16: =M16*N16 -> 6 | P16: =IF(O16>=20,"Critical",IF(O16>=12,"High",IF(O16>=6,"Medium",IF(O16>=2,"Low","Informational")))) -> Medium | Q16: Increase test coverage to 90%; implement chaos engineering; reduce MTTR to <1hr. | R16: Chief Technology Officer (CTO) | S16: 46173 | T16: 45931 | U16: In Progress
A17: TC-012 | B17: Intellectual Property Theft | C17: Theft of proprietary algorithms, source code or trade secrets by competitors or nation-state actors. | D17: Product & Engineering | E17: Chief Information Security Officer (CISO) | F17: 2 | G17: 5 | H17: =F17*G17 -> 10 | I17: =IF(H17>=20,"Critical",IF(H17>=12,"High",IF(H17>=6,"Medium",IF(H17>=2,"Low","Informational")))) -> Medium | J17: Code repository access controls; DLP on email/USB; NDA for all employees and contractors. | K17: Adequate | L17: Chief Information Security Officer (CISO) | M17: 1 | N17: 4 | O17: =M17*N17 -> 4 | P17: =IF(O17>=20,"Critical",IF(O17>=12,"High",IF(O17>=6,"Medium",IF(O17>=2,"Low","Informational")))) -> Low | Q17: Deploy UEBA for anomalous code access; conduct IP risk assessment; strengthen contractor controls. | R17: Chief Information Security Officer (CISO) | S17: 46265 | T17: 45901 | U17: Open
... A20: TC-015 | B20: Revenue Concentration Risk | C20: Over-reliance on top-3 customers (>50% ARR) creates existential risk if any customer churns. | D20: Financial | E20: Chief Financial Officer (CFO) | F20: 3 | G20: 5 | H20: =F20*G20 -> 15 | I20: =IF(H20>=20,"Critical",IF(H20>=12,"High",IF(H20>=6,"Medium",IF(H20>=2,"Low","Informational")))) -> High | J20: Customer success programme; churn early-warning model; NPS tracking monthly. | K20: Basic | L20: Chief Financial Officer (CFO) | M20: 3 | N20: 4 | O20: =M20*N20 -> 12 | P20: =IF(O20>=20,"Critical",IF(O20>=12,"High",IF(O20>=6,"Medium",IF(O20>=2,"Low","Informational")))) -> High | Q20: Diversify customer base; set concentration limit policy (no single customer >20% ARR). | R20: Chief Financial Officer (CFO) | S20: 46295 | T20: 45991 | U20: Open
A22: ⚡ Inherent Score (I) = Likelihood × Impact | Inherent Rating (J) auto-derived from Score | Residual Score (P) = Residual Likelihood × Residual Impact | Residual Rating (Q) auto-derived — change any input and all scores update instantly

Sheet Roles & Responsibilities
A1: GRC ROLES & RESPONSIBILITIES — RACI MATRIX
A2: R = Responsible A = Accountable C = Consulted I = Informed
A4: ROLE PROFILES
A5: Role | B5: Description | C5: Key Responsibilities
A6: Chief Executive Officer (CEO) | B6: Sets strategic direction, risk appetite and innovation culture. Accountable to the Board for company performance and ESG. | C6: • Strategic risk decision-making • Board & investor risk communication • Innovation & competitive strategy • ESG & sustainability leadership • M&A oversight • Crisis leadership
A7: Chief Technology Officer (CTO) | B7: Owns product engineering, platform reliability, technical architecture and AI/ML strategy. | C7: • Product engineering & SRE • Technical architecture decisions • Platform reliability & SLA • AI/ML product strategy • Tech debt & legacy management • Engineering team leadership
A8: Chief Risk Officer (CRO) | B8: Owns enterprise risk management framework. Provides risk oversight across technology, financial and operational domains. | C8: • ERM framework design • Risk appetite & register maintenance • Board risk reporting • Third-party & supply chain risk • Cyber risk governance • Emerging risk horizon scanning
A9: Chief Information Security Officer (CISO) | B9: Accountable for information security strategy, product security, cloud security and incident response. | C9: • Cyber risk & threat management • Security architecture & standards • SOC 2 / ISO 27001 compliance • Incident response & BCDR • Vendor security due diligence • Security awareness programme
A10: Chief People Officer (CPO) | B10: Responsible for talent acquisition, retention, DEI, remote workforce culture and HR compliance. | C10: • Talent acquisition & retention strategy • DEI programme & gender pay reporting • Remote work policy & culture • Learning & development (AI upskilling) • HR compliance & employment law • Succession planning
A11: Chief Financial Officer (CFO) | B11: Owns financial risk including revenue concentration, fraud, liquidity and financial regulatory compliance. | C11: • Revenue concentration monitoring • Financial controls & audit • Fraud risk management • Budget & forecasting • Investor reporting • Financial regulatory compliance
A12: Chief Compliance Officer (CCO) | B12: Manages regulatory compliance including GDPR, SOC 2, export controls and sector-specific obligations. | C12: • Regulatory compliance calendar • GDPR / privacy programme • SOC 2 / ISO 27001 certification • Export control & sanctions compliance • Policy lifecycle management • Compliance training & awareness
A13: Data Protection Officer (DPO) | B13: Statutory GDPR role. Manages privacy programme, DPIAs, data subject rights and regulatory liaison. | C13: • GDPR Article 30 records • DPIA programme • Data subject rights handling • Privacy by design advisory • Supervisory authority liaison • Cross-border data transfer compliance
A14: IT Director | B14: Responsible for cloud infrastructure, DevOps/SRE, PAM, toolchain security and IT vendor management. | C14: • Cloud infrastructure management • DevOps & CI/CD pipeline security • PAM & access control • IT vendor management • Disaster recovery & BCP • Technology change management
A15: Internal Audit Lead | B15: Provides independent assurance over security controls, financial controls and regulatory compliance posture. | C15: • Annual risk-based audit plan • SOC 2 control testing support • Financial controls assurance • Regulatory compliance audits • Penetration test oversight • Findings & action tracking
A18: RACI MATRIX — KEY GRC ACTIVITIES
A19: GRC Activity | B19: CEO | C19: CTO | D19: CRO | E19: CISO | F19: CFO | G19: CPO | H19: CCO | I19: DPO | J19: IT Dir | K19: Int Audit
A20: Enterprise Risk Framework | B20: I | C20: I | D20: A | E20: C | F20: C | G20: I | H20: C | I20: I | J20: I | K20: C
A21: Risk Appetite Statement | B21: A | C21: C | D21: R | E21: C | F21: C | G21: I | H21: C | I21: I | J21: I | K21: C
A22: Cloud Infrastructure Resilience | B22: I | C22: A | D22: C | E22: C | F22: I | G22: I | H22: I | I22: I | J22: R | K22: C
A23: Software Supply Chain Security | B23: I | C23: C | D23: C | E23: A | F23: I | G23: I | H23: I | I23: I | J23: R | K23: C
A24: Cyber Incident Response | B24: I | C24: C | D24: C | E24: A | F24: I | G24: I | H24: I | I24: I | J24: R | K24: I
A25: Customer Data / GDPR Compliance | B25: I | C25: I | D25: C | E25: C | F25: I | G25: I | H25: R | I25: A | J25: I | K25: C
A26: SOC 2 / ISO 27001 Certification | B26: I | C26: C | D26: C | E26: R | F26: I | G26: I | H26: A | I26: C | J26: R | K26: C
A27: Product Security | B27: I | C27: A | D27: C | E27: R | F27: I | G27: I | H27: I | I27: I | J27: C | K27: C
A28: Talent Acquisition & Retention | B28: I | C28: C | D28: I | E28: I | F28: I | G28: A | H28: I | I28: I | J28: I | K28: I
A29: AI / ML Skills Development | B29: C | C29: A | D29: I | E29: I | F29: I | G29: R | H29: I | I29: I | J29: I | K29: I
A30: DEI & HR Compliance | B30: I | C30: I | D30: I | E30: I | F30: C | G30: A | H30: R | I30: I | J30: I | K30: C
... A37: Board Risk Reporting | B37: A | C37: I | D37: R | E37: C | F37: C | G37: I | H37: C | I37: I | J37: I | K37: C
A39: A | B39: = Accountable
A40: R | B40: = Responsible
A41: C | B41: = Consulted
A42: I | B42: = Informed

Sheet Scoring Methodology
A1: GRC RISK SCORING METHODOLOGY
A2: ⚡ Inherent Score = Likelihood × Impact | Residual Score = Residual Likelihood × Residual Impact | All scores recalculate automatically when inputs change
A4: LIKELIHOOD SCALE | E4: CONTROL EFFECTIVENESS
A5: Score | B5: Rating | C5: Definition | E5: Rating | F5: Reduction | G5: Criteria
A6: 5 | B6: Very High | C6: Almost certain — continuous threat; exploited regularly | E6: Strong | F6: 55% | G6: SOC 2 II / ISO 27001 certified; tested; no gaps
A7: 4 | B7: High | C7: Likely — expected to occur within 12 months | E7: Adequate | F7: 35% | G7: Controls present; minor gaps; cert in progress
A8: 3 | B8: Medium | C8: Possible — could occur within 1–3 years | E8: Basic | F8: 15% | G8: Partial controls; significant gaps; largely manual
A9: 2 | B9: Low | C9: Unlikely — may occur within 3–5 years | E9: Weak | F9: 0% | G9: Insufficient controls; critical gaps
A10: 1 | B10: Very Low | C10: Rare — less than once in 5 years
E11: THREE LINES OF DEFENCE
A12: IMPACT SCALE | E12: Line | F12: Owner | G12: Role
A13: Score | B13: Rating | C13: Definition | E13: 1st | F13: Business Unit / Department Leads | G13: Day-to-day risk ownership & control operation
A14: 5 | B14: Catastrophic | C14: Existential threat; regulatory closure; loss > £50M | E14: 2nd | F14: CRO / CCO / CISO / HR | G14: Risk framework, policy, oversight & challenge
A15: 4 | B15: Major | C15: Material harm; loss £10M–£50M; significant regulatory sanction | E15: 3rd | F15: Internal Audit | G15: Independent assurance over risk & controls
A16: 3 | B16: Moderate | C16: Disruption; loss £1M–£10M; regulatory attention
A17: 2 | B17: Minor | C17: Limited impact; loss £100K–£1M; manageable
A18: 1 | B18: Negligible | C18: Minimal; loss < £100K; quickly resolved
A20: RISK RATING MATRIX (Inherent)
A21: Score | B21: Rating | C21: Required Response
A22: 20–25 | B22: Critical | C22: Board escalation within 24 hrs. Emergency treatment plan.
A23: 12–19 | B23: High | C23: Escalate to CRO. Active remediation. Review within 30 days.
A24: 6–11 | B24: Medium | C24: Assign owner. Treatment plan within 60 days. Quarterly monitoring.
A25: 2–5 | B25: Low | C25: Accept or treat. Standard annual review cycle.
A26: 1 | B26: Informational | C26: Log and monitor. Annual review.

Sheet Executive Dashboard
A1: GRC EXECUTIVE RISK DASHBOARD — KTECH
A2: Reporting Period: Q1 2026 | Prepared by: Senior GRC Analyst | As of 07 April 2026 | All metrics update automatically from the Risk Register
A4: Total Risks | D4: Critical / High | G4: Open Risks | J4: Avg Residual Score
A5: =COUNTA('GRC Risk Register'!A6:A20) -> 15 | D5: =COUNTIF('GRC Risk Register'!P6:P20,"Critical")+COUNTIF('GRC Risk Register'!P6:P20,"High") -> 2 | G5: =COUNTIF('GRC Risk Register'!U6:U20,"Open")+COUNTIF('GRC Risk Register'!U6:U20,"In Progress") -> 14 | J5: =ROUND(AVERAGE('GRC Risk Register'!O6:O20),1) -> 7.4
A8: Closed / Accepted | D8: Overdue Actions | G8: IT / Tech Risks | J8: HR / People Risks
A9: =COUNTIF('GRC Risk Register'!U6:U20,"Closed")+COUNTIF('GRC Risk Register'!U6:U20,"Accepted") -> 1 | D9: =SUMPRODUCT(('GRC Risk Register'!S6:S20<ReportDate)*('GRC Risk Register'!S6:S20<>"")*('GRC Risk Register'!U6:U20<>"Closed")*('GRC Risk Register'!U6:U20<>"Accepted")) -> 0 | G9: =COUNTIF('GRC Risk Register'!D6:D20,"Technology / IT")+COUNTIF('GRC Risk Register'!D6:D20,"Information Technology")+COUNTIF('GRC Risk Register'!D6:D20,"Product & Engineering") -> 7 | J9: =COUNTIF('GRC Risk Register'!D6:D20,"Human Resources") -> 4
A15: RISK DISTRIBUTION BY DOMAIN ⚡ Auto-updates
A16: Domain | B16: Total | C16: Critical | D16: High | E16: Medium | F16: Low
A17: Governance | B17: =COUNTIF('GRC Risk Register'!D6:D20,"Governance") -> 1 | C17: =COUNTIFS('GRC Risk Register'!D6:D20,"Governance",'GRC Risk Register'!P6:P20,"Critical") -> 0 | D17: =COUNTIFS('GRC Risk Register'!D6:D20,"Governance",'GRC Risk Register'!P6:P20,"High") -> 0 | E17: =COUNTIFS('GRC Risk Register'!D6:D20,"Governance",'GRC Risk Register'!P6:P20,"Medium") -> 1 | F17: =COUNTIFS('GRC Risk Register'!D6:D20,"Governance",'GRC Risk Register'!P6:P20,"Low") -> 0
A18: Information Technology | B18: =COUNTIF('GRC Risk Register'!D6:D20,"Information Technology") -> 5 | C18: =COUNTIFS('GRC Risk Register'!D6:D20,"Information Technology",'GRC Risk Register'!P6:P20,"Critical") -> 0 | D18: =COUNTIFS('GRC Risk Register'!D6:D20,"Information Technology",'GRC Risk Register'!P6:P20,"High") -> 0 | E18: =COUNTIFS('GRC Risk Register'!D6:D20,"Information Technology",'GRC Risk Register'!P6:P20,"Medium") -> 4 | F18: =COUNTIFS('GRC Risk Register'!D6:D20,"Information Technology",'GRC Risk Register'!P6:P20,"Low") -> 1
A19: Human Resources | B19: =COUNTIF('GRC Risk Register'!D6:D20,"Human Resources") -> 4 | C19: =COUNTIFS('GRC Risk Register'!D6:D20,"Human Resources",'GRC Risk Register'!P6:P20,"Critical") -> 0 | D19: =COUNTIFS('GRC Risk Register'!D6:D20,"Human Resources",'GRC Risk Register'!P6:P20,"High") -> 1 | E19: =COUNTIFS('GRC Risk Register'!D6:D20,"Human Resources",'GRC Risk Register'!P6:P20,"Medium") -> 2 | F19: =COUNTIFS('GRC Risk Register'!D6:D20,"Human Resources",'GRC Risk Register'!P6:P20,"Low") -> 1
A20: Product & Engineering | B20: =COUNTIF('GRC Risk Register'!D6:D20,"Product & Engineering") -> 2 | C20: =COUNTIFS('GRC Risk Register'!D6:D20,"Product & Engineering",'GRC Risk Register'!P6:P20,"Critical") -> 0 | D20: =COUNTIFS('GRC Risk Register'!D6:D20,"Product & Engineering",'GRC Risk Register'!P6:P20,"High") -> 0 | E20: =COUNTIFS('GRC Risk Register'!D6:D20,"Product & Engineering",'GRC Risk Register'!P6:P20,"Medium") -> 1 | F20: =COUNTIFS('GRC Risk Register'!D6:D20,"Product & Engineering",'GRC Risk Register'!P6:P20,"Low") -> 1
A21: Compliance | B21: =COUNTIF('GRC Risk Register'!D6:D20,"Compliance") -> 1 | C21: =COUNTIFS('GRC Risk Register'!D6:D20,"Compliance",'GRC Risk Register'!P6:P20,"Critical") -> 0 | D21: =COUNTIFS('GRC Risk Register'!D6:D20,"Compliance",'GRC Risk Register'!P6:P20,"High") -> 0 | E21: =COUNTIFS('GRC Risk Register'!D6:D20,"Compliance",'GRC Risk Register'!P6:P20,"Medium") -> 0 | F21: =COUNTIFS('GRC Risk Register'!D6:D20,"Compliance",'GRC Risk Register'!P6:P20,"Low") -> 1
A22: Financial | B22: =COUNTIF('GRC Risk Register'!D6:D20,"Financial") -> 1 | C22: =COUNTIFS('GRC Risk Register'!D6:D20,"Financial",'GRC Risk Register'!P6:P20,"Critical") -> 0 | D22: =COUNTIFS('GRC Risk Register'!D6:D20,"Financial",'GRC Risk Register'!P6:P20,"High") -> 1 | E22: =COUNTIFS('GRC Risk Register'!D6:D20,"Financial",'GRC Risk Register'!P6:P20,"Medium") -> 0 | F22: =COUNTIFS('GRC Risk Register'!D6:D20,"Financial",'GRC Risk Register'!P6:P20,"Low") -> 0
A23: Strategic | B23: =COUNTIF('GRC Risk Register'!D6:D20,"Strategic") -> 1 | C23: =COUNTIFS('GRC Risk Register'!D6:D20,"Strategic",'GRC Risk Register'!P6:P20,"Critical") -> 0 | D23: =COUNTIFS('GRC Risk Register'!D6:D20,"Strategic",'GRC Risk Register'!P6:P20,"High") -> 0 | E23: =COUNTIFS('GRC Risk Register'!D6:D20,"Strategic",'GRC Risk Register'!P6:P20,"Medium") -> 1 | F23: =COUNTIFS('GRC Risk Register'!D6:D20,"Strategic",'GRC Risk Register'!P6:P20,"Low") -> 0
A26: RISK OWNERSHIP SUMMARY ⚡ Auto-updates
A27: Role | B27: Owned | C27: Open | D27: In Progress | E27: Closed | F27: Avg Residual
A28: CTO | B28: =COUNTIF('GRC Risk Register'!E6:E20,"Chief Technology Officer (CTO)") -> 1 | C28: =COUNTIFS('GRC Risk Register'!E6:E20,"Chief Technology Officer (CTO)",'GRC Risk Register'!U6:U20,"Open") -> 0 | D28: =COUNTIFS('GRC Risk Register'!E6:E20,"Chief Technology Officer (CTO)",'GRC Risk Register'!U6:U20,"In Progress") -> 1 | E28: =COUNTIFS('GRC Risk Register'!E6:E20,"Chief Technology Officer (CTO)",'GRC Risk Register'!U6:U20,"Closed") -> 0 | F28: =IFERROR(ROUND(AVERAGEIF('GRC Risk Register'!E6:E20,"Chief Technology Officer (CTO)",'GRC Risk Register'!O6:O20),1),"-") -> 6
A29: CRO | B29: =COUNTIF('GRC Risk Register'!E6:E20,"Chief Risk Officer (CRO)") -> 1 | C29: =COUNTIFS('GRC Risk Register'!E6:E20,"Chief Risk Officer (CRO)",'GRC Risk Register'!U6:U20,"Open") -> 0 | D29: =COUNTIFS('GRC Risk Register'!E6:E20,"Chief Risk Officer (CRO)",'GRC Risk Register'!U6:U20,"In Progress") -> 1 | E29: =COUNTIFS('GRC Risk Register'!E6:E20,"Chief Risk Officer (CRO)",'GRC Risk Register'!U6:U20,"Closed") -> 0 | F29: =IFERROR(ROUND(AVERAGEIF('GRC Risk Register'!E6:E20,"Chief Risk Officer (CRO)",'GRC Risk Register'!O6:O20),1),"-") -> 9
A30: CISO | B30: =COUNTIF('GRC Risk Register'!E6:E20,"Chief Information Security Officer (CISO)") -> 4 | C30: =COUNTIFS('GRC Risk Register'!E6:E20,"Chief Information Security Officer (CISO)",'GRC Risk Register'!U6:U20,"Open") -> 3 | D30: =COUNTIFS('GRC Risk Register'!E6:E20,"Chief Information Security Officer (CISO)",'GRC Risk Register'!U6:U20,"In Progress") -> 1 | E30: =COUNTIFS('GRC Risk Register'!E6:E20,"Chief Information Security Officer (CISO)",'GRC Risk Register'!U6:U20,"Closed") -> 0 | F30: =IFERROR(ROUND(AVERAGEIF('GRC Risk Register'!E6:E20,"Chief Information Security Officer (CISO)",'GRC Risk Register'!O6:O20),1),"-") -> 7
A31: CPO | B31: =COUNTIF('GRC Risk Register'!E6:E20,"Chief People Officer (CPO)") -> 4 | C31: =COUNTIFS('GRC Risk Register'!E6:E20,"Chief People Officer (CPO)",'GRC Risk Register'!U6:U20,"Open") -> 2 | D31: =COUNTIFS('GRC Risk Register'!E6:E20,"Chief People Officer (CPO)",'GRC Risk Register'!U6:U20,"In Progress") -> 2 | E31: =COUNTIFS('GRC Risk Register'!E6:E20,"Chief People Officer (CPO)",'GRC Risk Register'!U6:U20,"Closed") -> 0 | F31: =IFERROR(ROUND(AVERAGEIF('GRC Risk Register'!E6:E20,"Chief People Officer (CPO)",'GRC Risk Register'!O6:O20),1),"-") -> 7.5
A32: CFO | B32: =COUNTIF('GRC Risk Register'!E6:E20,"Chief Financial Officer (CFO)") -> 1 | C32: =COUNTIFS('GRC Risk Register'!E6:E20,"Chief Financial Officer (CFO)",'GRC Risk Register'!U6:U20,"Open") -> 1 | D32: =COUNTIFS('GRC Risk Register'!E6:E20,"Chief Financial Officer (CFO)",'GRC Risk Register'!U6:U20,"In Progress") -> 0 | E32: =COUNTIFS('GRC Risk Register'!E6:E20,"Chief Financial Officer (CFO)",'GRC Risk Register'!U6:U20,"Closed") -> 0 | F32: =IFERROR(ROUND(AVERAGEIF('GRC Risk Register'!E6:E20,"Chief Financial Officer (CFO)",'GRC Risk Register'!O6:O20),1),"-") -> 12
A33: CCO | B33: =COUNTIF('GRC Risk Register'!E6:E20,"Chief Compliance Officer (CCO)") -> 1 | C33: =COUNTIFS('GRC Risk Register'!E6:E20,"Chief Compliance Officer (CCO)",'GRC Risk Register'!U6:U20,"Open") -> 0 | D33: =COUNTIFS('GRC Risk Register'!E6:E20,"Chief Compliance Officer (CCO)",'GRC Risk Register'!U6:U20,"In Progress") -> 0 | E33: =COUNTIFS('GRC Risk Register'!E6:E20,"Chief Compliance Officer (CCO)",'GRC Risk Register'!U6:U20,"Closed") -> 1 | F33: =IFERROR(ROUND(AVERAGEIF('GRC Risk Register'!E6:E20,"Chief Compliance Officer (CCO)",'GRC Risk Register'!O6:O20),1),"-") -> 4

Sheet Heat Map
B1: Risk Prioritisation — Heat Map
B2: KTECH Residual Risk View | Q1 2026
C4: ← MORE CONTROLLED VULNERABILITY / LIKELIHOOD LESS CONTROLLED →
A5: IMPACT ↑ | B5: 5 – Catastrophic | C5: {=IFERROR(_xlfn.TEXTJOIN(CHAR(10),TRUE,IF(('GRC Risk Register'!M6:M20=1)*('GRC Risk Register'!N6:N20=5),'GRC Risk Register'!A6:A20,"")),"")} -> TC-002 | D5: {=IFERROR(_xlfn.TEXTJOIN(CHAR(10),TRUE,IF(('GRC Risk Register'!M6:M20=2)*('GRC Risk Register'!N6:N20=5),'GRC Risk Register'!A6:A20,"")),"")} -> TC-003 | E5: {=IFERROR(_xlfn.TEXTJOIN(CHAR(10),TRUE,IF(('GRC Risk Register'!M6:M20=3)*('GRC Risk Register'!N6:N20=5),'GRC Risk Register'!A6:A20,"")),"")} | F5: {=IFERROR(_xlfn.TEXTJOIN(CHAR(10),TRUE,IF(('GRC Risk Register'!M6:M20=4)*('GRC Risk Register'!N6:N20=5),'GRC Risk Register'!A6:A20,"")),"")} | G5: {=IFERROR(_xlfn.TEXTJOIN(CHAR(10),TRUE,IF(('GRC Risk Register'!M6:M20=5)*('GRC Risk Register'!N6:N20=5),'GRC Risk Register'!A6:A20,"")),"")} | J5: RISK RATING LEGEND
B6: 4 – Major | C6: {=IFERROR(_xlfn.TEXTJOIN(CHAR(10),TRUE,IF(('GRC Risk Register'!M6:M20=1)*('GRC Risk Register'!N6:N20=4),'GRC Risk Register'!A6:A20,"")),"")} -> TC-012 TC-013 | D6: {=IFERROR(_xlfn.TEXTJOIN(CHAR(10),TRUE,IF(('GRC Risk Register'!M6:M20=2)*('GRC Risk Register'!N6:N20=4),'GRC Risk Register'!A6:A20,"")),"")} -> TC-004 TC-005 | E6: {=IFERROR(_xlfn.TEXTJOIN(CHAR(10),TRUE,IF(('GRC Risk Register'!M6:M20=3)*('GRC Risk Register'!N6:N20=4),'GRC Risk Register'!A6:A20,"")),"")} -> TC-007 TC-015 | F6: {=IFERROR(_xlfn.TEXTJOIN(CHAR(10),TRUE,IF(('GRC Risk Register'!M6:M20=4)*('GRC Risk Register'!N6:N20=4),'GRC Risk Register'!A6:A20,"")),"")} | G6: {=IFERROR(_xlfn.TEXTJOIN(CHAR(10),TRUE,IF(('GRC Risk Register'!M6:M20=5)*('GRC Risk Register'!N6:N20=4),'GRC Risk Register'!A6:A20,"")),"")} | J6: HIGH | K6: Residual score 12–19
B7: 3 – Moderate | C7: {=IFERROR(_xlfn.TEXTJOIN(CHAR(10),TRUE,IF(('GRC Risk Register'!M6:M20=1)*('GRC Risk Register'!N6:N20=3),'GRC Risk Register'!A6:A20,"")),"")} -> TC-010 | D7: {=IFERROR(_xlfn.TEXTJOIN(CHAR(10),TRUE,IF(('GRC Risk Register'!M6:M20=2)*('GRC Risk Register'!N6:N20=3),'GRC Risk Register'!A6:A20,"")),"")} -> TC-006 TC-009 TC-011 | E7: {=IFERROR(_xlfn.TEXTJOIN(CHAR(10),TRUE,IF(('GRC Risk Register'!M6:M20=3)*('GRC Risk Register'!N6:N20=3),'GRC Risk Register'!A6:A20,"")),"")} -> TC-001 TC-008 TC-014 | F7: {=IFERROR(_xlfn.TEXTJOIN(CHAR(10),TRUE,IF(('GRC Risk Register'!M6:M20=4)*('GRC Risk Register'!N6:N20=3),'GRC Risk Register'!A6:A20,"")),"")} | G7: {=IFERROR(_xlfn.TEXTJOIN(CHAR(10),TRUE,IF(('GRC Risk Register'!M6:M20=5)*('GRC Risk Register'!N6:N20=3),'GRC Risk Register'!A6:A20,"")),"")} | K7: Escalate to CRO. Active remediation.
B8: 2 – Minor | C8: {=IFERROR(_xlfn.TEXTJOIN(CHAR(10),TRUE,IF(('GRC Risk Register'!M6:M20=1)*('GRC Risk Register'!N6:N20=2),'GRC Risk Register'!A6:A20,"")),"")} | D8: {=IFERROR(_xlfn.TEXTJOIN(CHAR(10),TRUE,IF(('GRC Risk Register'!M6:M20=2)*('GRC Risk Register'!N6:N20=2),'GRC Risk Register'!A6:A20,"")),"")} | E8: {=IFERROR(_xlfn.TEXTJOIN(CHAR(10),TRUE,IF(('GRC Risk Register'!M6:M20=3)*('GRC Risk Register'!N6:N20=2),'GRC Risk Register'!A6:A20,"")),"")} | F8: {=IFERROR(_xlfn.TEXTJOIN(CHAR(10),TRUE,IF(('GRC Risk Register'!M6:M20=4)*('GRC Risk Register'!N6:N20=2),'GRC Risk Register'!A6:A20,"")),"")} | G8: {=IFERROR(_xlfn.TEXTJOIN(CHAR(10),TRUE,IF(('GRC Risk Register'!M6:M20=5)*('GRC Risk Register'!N6:N20=2),'GRC Risk Register'!A6:A20,"")),"")} | J8: MEDIUM | K8: Residual score 6–11
B9: 1 – Negligible | C9: {=IFERROR(_xlfn.TEXTJOIN(CHAR(10),TRUE,IF(('GRC Risk Register'!M6:M20=1)*('GRC Risk Register'!N6:N20=1),'GRC Risk Register'!A6:A20,"")),"")} | D9: {=IFERROR(_xlfn.TEXTJOIN(CHAR(10),TRUE,IF(('GRC Risk Register'!M6:M20=2)*('GRC Risk Register'!N6:N20=1),'GRC Risk Register'!A6:A20,"")),"")} | E9: {=IFERROR(_xlfn.TEXTJOIN(CHAR(10),TRUE,IF(('GRC Risk Register'!M6:M20=3)*('GRC Risk Register'!N6:N20=1),'GRC Risk Register'!A6:A20,"")),"")} | F9: {=IFERROR(_xlfn.TEXTJOIN(CHAR(10),TRUE,IF(('GRC Risk Register'!M6:M20=4)*('GRC Risk Register'!N6:N20=1),'GRC Risk Register'!A6:A20,"")),"")} | G9: {=IFERROR(_xlfn.TEXTJOIN(CHAR(10),TRUE,IF(('GRC Risk Register'!M6:M20=5)*('GRC Risk Register'!N6:N20=1),'GRC Risk Register'!A6:A20,"")),"")} | K9: Owner assigned. Quarterly monitoring.
C10: 1 – Rare | D10: 2 – Unlikely | E10: 3 – Possible | F10: 4 – Likely | G10: 5 – Almost Certain | J10: LOW | K10: Residual score 2–5
A11: RISK INDEX | K11: Accept or treat. Annual review.
A12: Risk ID | B12: Risk Title | C12: Domain | D12: Res. Likelihood | E12: Res. Impact | F12: Residual Score | G12: Rating
A13: ='GRC Risk Register'!A6 -> TC-001 | B13: ='GRC Risk Register'!B6 -> Inadequate Enterprise Risk Governance | C13: ='GRC Risk Register'!D6 -> Governance | D13: ='GRC Risk Register'!M6 -> 3 | E13: ='GRC Risk Register'!N6 -> 3 | F13: ='GRC Risk Register'!O6 -> 9 | G13: ='GRC Risk Register'!P6 -> Medium
A14: ='GRC Risk Register'!A7 -> TC-002 | B14: ='GRC Risk Register'!B7 -> Cloud Infrastructure Failure | C14: ='GRC Risk Register'!D7 -> Information Technology | D14: ='GRC Risk Register'!M7 -> 1 | E14: ='GRC Risk Register'!N7 -> 5 | F14: ='GRC Risk Register'!O7 -> 5 | G14: ='GRC Risk Register'!P7 -> Low
A15: ='GRC Risk Register'!A8 -> TC-003 | B15: ='GRC Risk Register'!B8 -> Software Supply Chain Attack | C15: ='GRC Risk Register'!D8 -> Information Technology | D15: ='GRC Risk Register'!M8 -> 2 | E15: ='GRC Risk Register'!N8 -> 5 | F15: ='GRC Risk Register'!O8 -> 10 | G15: ='GRC Risk Register'!P8 -> Medium
A16: ='GRC Risk Register'!A9 -> TC-004 | B16: ='GRC Risk Register'!B9 -> Zero-Day Vulnerability Exploitation | C16: ='GRC Risk Register'!D9 -> Information Technology | D16: ='GRC Risk Register'!M9 -> 2 | E16: ='GRC Risk Register'!N9 -> 4 | F16: ='GRC Risk Register'!O9 -> 8 | G16: ='GRC Risk Register'!P9 -> Medium
A17: ='GRC Risk Register'!A10 -> TC-005 | B17: ='GRC Risk Register'!B10 -> Customer Data Breach (GDPR/CCPA) | C17: ='GRC Risk Register'!D10 -> Information Technology | D17: ='GRC Risk Register'!M10 -> 2 | E17: ='GRC Risk Register'!N10 -> 4 | F17: ='GRC Risk Register'!O10 -> 8 | G17: ='GRC Risk Register'!P10 -> Medium
A18: ='GRC Risk Register'!A11 -> TC-006 | B18: ='GRC Risk Register'!B11 -> Privileged Access & Insider Threat | C18: ='GRC Risk Register'!D11 -> Information Technology | D18: ='GRC Risk Register'!M11 -> 2 | E18: ='GRC Risk Register'!N11 -> 3 | F18: ='GRC Risk Register'!O11 -> 6 | G18: ='GRC Risk Register'!P11 -> Medium
A19: ='GRC Risk Register'!A12 -> TC-007 | B19: ='GRC Risk Register'!B12 -> Developer Talent Attrition | C19: ='GRC Risk Register'!D12 -> Human Resources | D19: ='GRC Risk Register'!M12 -> 3 | E19: ='GRC Risk Register'!N12 -> 4 | F19: ='GRC Risk Register'!O12 -> 12 | G19: ='GRC Risk Register'!P12 -> High
A20: ='GRC Risk Register'!A13 -> TC-008 | B20: ='GRC Risk Register'!B13 -> AI / ML Skills Gap | C20: ='GRC Risk Register'!D13 -> Human Resources | D20: ='GRC Risk Register'!M13 -> 3 | E20: ='GRC Risk Register'!N13 -> 3 | F20: ='GRC Risk Register'!O13 -> 9 | G20: ='GRC Risk Register'!P13 -> Medium
A21: ='GRC Risk Register'!A14 -> TC-009 | B21: ='GRC Risk Register'!B14 -> Remote Work Security & Culture Risk | C21: ='GRC Risk Register'!D14 -> Human Resources | D21: ='GRC Risk Register'!M14 -> 2 | E21: ='GRC Risk Register'!N14 -> 3 | F21: ='GRC Risk Register'!O14 -> 6 | G21: ='GRC Risk Register'!P14 -> Medium
A22: ='GRC Risk Register'!A15 -> TC-010 | B22: ='GRC Risk Register'!B15 -> Diversity, Equity & Inclusion (DEI) Compliance | C22: ='GRC Risk Register'!D15 -> Human Resources | D22: ='GRC Risk Register'!M15 -> 1 | E22: ='GRC Risk Register'!N15 -> 3 | F22: ='GRC Risk Register'!O15 -> 3 | G22: ='GRC Risk Register'!P15 -> Low
A23: ='GRC Risk Register'!A16 -> TC-011 | B23: ='GRC Risk Register'!B16 -> Critical Product Defect / Outage | C23: ='GRC Risk Register'!D16 -> Product & Engineering | D23: ='GRC Risk Register'!M16 -> 2 | E23: ='GRC Risk Register'!N16 -> 3 | F23: ='GRC Risk Register'!O16 -> 6 | G23: ='GRC Risk Register'!P16 -> Medium
A24: ='GRC Risk Register'!A17 -> TC-012 | B24: ='GRC Risk Register'!B17 -> Intellectual Property Theft | C24: ='GRC Risk Register'!D17 -> Product & Engineering | D24: ='GRC Risk Register'!M17 -> 1 | E24: ='GRC Risk Register'!N17 -> 4 | F24: ='GRC Risk Register'!O17 -> 4 | G24: ='GRC Risk Register'!P17 -> Low
... A27: ='GRC Risk Register'!A20 -> TC-015 | B27: ='GRC Risk Register'!B20 -> Revenue Concentration Risk | C27: ='GRC Risk Register'!D20 -> Financial | D27: ='GRC Risk Register'!M20 -> 3 | E27: ='GRC Risk Register'!N20 -> 4 | F27: ='GRC Risk Register'!O20 -> 12 | G27: ='GRC Risk Register'!P20 -> High
